[
  {
    "ImportType": "CARRYOVER",
    "Count": 1,
    "OldestDate": "2025-06-01T00:00:00",
    "NewestDate": "2025-06-01T00:00:00"
  },
  {
    "ImportType": "IMPORT",
    "Count": 180,
    "OldestDate": "2025-06-01T00:00:00",
    "NewestDate": "2025-07-20T00:00:00"
  },
  {
    "ImportType": "INIT",
    "Count": 1,
    "OldestDate": "2025-05-31T00:00:00",
    "NewestDate": "2025-05-31T00:00:00"
  },
  {
    "ImportType": "UNKNOWN",
    "Count": 3,
    "OldestDate": "2025-06-01T00:00:00",
    "NewestDate": "2025-06-02T00:00:00"
  }
]